{
    "CLASS_NAME": "LightSource",
    "name": "ESRF_ID24_HighBeta_PPU32_2",
    "electron_beam": {
        "CLASS_NAME": "ElectronBeam",
        "energy_in_GeV": 6.037,
        "energy_spread": 0.0011,
        "current": 0.2,
        "number_of_bunches": 1,
        "moment_xx": 1.72200930841e-07,
        "moment_xxp": 0.0,
        "moment_xpxp": 1.0639716201e-10,
        "moment_yy": 1.17891282609e-11,
        "moment_yyp": 0.0,
        "moment_ypyp": 1.3571784004e-12
    },
    "magnetic_structure": {
        "CLASS_NAME": "Undulator",
        "K_vertical": 1.928617414,
        "K_horizontal": 0.0,
        "period_length": 0.032,
        "number_of_periods": 50
    }
}